{"lastrevid": 577624571, "pageid": 1349984, "canonicalurl": "http://en.wikipedia.org/wiki/Talk:Inversive_geometry", "links": [{"ns": 0, "title": "AdS/CFT"}, {"ns": 0, "title": "AdS/CFT duality"}, {"ns": 0, "title": "Analytic geometry"}, {"ns": 0, "title": "Cayley-Klein metric"}, {"ns": 0, "title": "Circle inversion"}, {"ns": 0, "title": "Circular transformation"}, {"ns": 0, "title": "Cut-the-knot"}, {"ns": 0, "title": "Euclidean plane isometry"}, {"ns": 0, "title": "Inverse (mathematics)"}, {"ns": 0, "title": "Inverse curve"}, {"ns": 0, "title": "Inversion (geometry)"}, {"ns": 0, "title": "Inversion in a point"}, {"ns": 0, "title": "Inversive geometry"}, {"ns": 0, "title": "Inversive ring geometry"}, {"ns": 0, "title": "Julian Coolidge"}, {"ns": 0, "title": "Klein model"}, {"ns": 0, "title": "Math style manual"}, {"ns": 0, "title": "Mathematics"}, {"ns": 0, "title": "Michel Chasles"}, {"ns": 0, "title": "M\u00f6bius transformation"}, {"ns": 0, "title": "Pappus chain"}, {"ns": 0, "title": "Poincare disk model"}, {"ns": 0, "title": "Poincare half-plane model"}, {"ns": 0, "title": "Reflection (mathematics)"}, {"ns": 0, "title": "Stereographic projection"}, {"ns": 0, "title": "Subscript and superscript"}, {"ns": 0, "title": "Unit sphere"}, {"ns": 0, "title": "Wick rotation"}], "title": "Talk:Inversive geometry", "editurl": "http://en.wikipedia.org/w/index.php?title=Talk:Inversive_geometry&action=edit", "contentmodel": "wikitext", "length": 27057, "pagelanguage": "en", "touched": "2015-04-18T03:53:14Z", "ns": 1, "fullurl": "http://en.wikipedia.org/wiki/Talk:Inversive_geometry", "categories": [{"ns": 14, "title": "Category:C-Class mathematics articles"}, {"ns": 14, "title": "Category:High-Priority mathematics articles"}, {"ns": 14, "title": "Category:Mathematics articles related to geometry"}], "revisions": [{"comment": "/* Magnus or Steiner? */ Coolidge quotes", "sha1": "7b8b7f6fa74115a2978124645cabf575dfddbf68", "timestamp": "2013-10-17T21:03:54Z", "userid": 92899, "revid": 577624571, "user": "Rgdboer", "parentid": 577475080, "size": 27057}, {"comment": "/* Magnus or Steiner? */ neither", "sha1": "7633c57dbbba3a581333946550664531b8d78cba", "timestamp": "2013-10-16T20:06:25Z", "userid": 92899, "revid": 577475080, "user": "Rgdboer", "parentid": 577447821, "size": 26266}, {"comment": "/* Magnus or Steiner? */ r", "sha1": "e8b46a7aaafced32fc0951955532651b72c3708d", "timestamp": "2013-10-16T16:24:39Z", "userid": 13428914, "revid": 577447821, "user": "Wcherowi", "parentid": 577419446, "size": 26004}, {"comment": "Signing comment by [[Special:Contributions/86.185.249.166|86.185.249.166]] - \"/* Magnus or Steiner? */ new section\"", "sha1": "775cb6ccee758fb723305fd1295cc0db2c5c5df0", "timestamp": "2013-10-16T12:14:05Z", "userid": 4936590, "revid": 577419446, "user": "SineBot", "parentid": 577419326, "size": 24966}, {"comment": "/* Magnus or Steiner? */ new section", "sha1": "c5323fd0a3dc08c629b805197da8368ea0cc821b", "timestamp": "2013-10-16T12:12:56Z", "userid": 0, "revid": 577419326, "anon": "", "user": "86.185.249.166", "parentid": 563241180, "size": 24661}, {"comment": "", "sha1": "71a6cb58c9b4ad977c01e2c788863a78eb4f2f89", "timestamp": "2013-07-07T14:11:00Z", "userid": 2849695, "revid": 563241180, "user": "Weburbia", "parentid": 531108380, "size": 24284}, {"comment": "/* New pic, new problem */", "sha1": "8f483d2f76ca091139774c6558dcc26e87270419", "timestamp": "2013-01-03T16:41:20Z", "userid": 13428914, "revid": 531108380, "user": "Wcherowi", "parentid": 530972933, "size": 23842}, {"comment": "/* New pic, new problem */", "sha1": "3daaa2b52e7b8afed1421bf5a398f141b4290e3f", "timestamp": "2013-01-02T20:40:01Z", "userid": 13428914, "revid": 530972933, "user": "Wcherowi", "parentid": 530902862, "size": 23569}, {"comment": "/* Bad diagram */ still bad", "sha1": "35227dde8c352006e11de7b925e05785f40a6dd2", "timestamp": "2013-01-02T11:24:21Z", "userid": 17427479, "revid": 530902862, "user": "Dave Bowman - Discovery Won", "parentid": 464873823, "size": 22968}, {"comment": "/* Cayley */ No he didn't", "sha1": "b088050651903fbe61509fba2c6bb9490f637604", "timestamp": "2011-12-09T01:10:06Z", "userid": 13428914, "revid": 464873823, "user": "Wcherowi", "parentid": 464839016, "size": 21945}, {"comment": "/* Cayley */ add link", "sha1": "17c12e15872676634316d1165478d28c0ccb0926", "timestamp": "2011-12-08T21:29:42Z", "userid": 92899, "revid": 464839016, "user": "Rgdboer", "parentid": 464838568, "size": 20925}, {"comment": "/* Cayley */ new section", "sha1": "469311acb638e31cd0015a22ba25d936496c73e3", "timestamp": "2011-12-08T21:27:10Z", "userid": 92899, "revid": 464838568, "user": "Rgdboer", "parentid": 463617789, "size": 20795}, {"comment": "/* Bad diagram */ Oops", "sha1": "d7c8a455686275f237f5b3ff0f13aab7acc2fb7c", "timestamp": "2011-12-02T05:11:37Z", "userid": 13428914, "revid": 463617789, "user": "Wcherowi", "parentid": 463467421, "size": 19841}, {"comment": "/* Bad diagram */ Use SVG", "sha1": "8f3110eb7f3b427c85e2e326f743acee35f1dfda", "timestamp": "2011-12-01T08:28:24Z", "userid": 433687, "revid": 463467421, "user": "RDBury", "parentid": 463363017, "size": 19236}, {"comment": "/* Bad diagram */ new section", "sha1": "262267efa074f79d596e7c430d0125bec390917f", "timestamp": "2011-11-30T21:36:32Z", "userid": 13428914, "revid": 463363017, "user": "Wcherowi", "parentid": 429996516, "size": 19088}, {"comment": "this is not start-class", "sha1": "df1aaa1851f8e7357100618257472b6ffecba1d3", "timestamp": "2011-05-20T05:16:45Z", "userid": 258000, "revid": 429996516, "user": "King of Hearts", "parentid": 390270288, "size": 18299}, {"comment": "/* The basic inversion equation is lacking */Subst: {{unsigned}}  (& regularise templates)", "sha1": "0331d3fbfffa826c8561d4a58dd7ff93b7b5f727", "timestamp": "2010-10-12T12:25:10Z", "userid": 433328, "revid": 390270288, "user": "SmackBot", "parentid": 329209936, "size": 18303}, {"comment": "/* The basic inversion equation is lacking */ Response to OP", "sha1": "040b217901615813126339b6fb697cea0646959f", "timestamp": "2009-12-02T08:30:08Z", "userid": 433687, "revid": 329209936, "user": "RDBury", "parentid": 329110052, "size": 18067}, {"comment": "/* The basic inversion equation is lacking */", "sha1": "94b3c51578cdc06ef42ae228c23471e2b02865c3", "timestamp": "2009-12-01T21:05:58Z", "userid": 4626, "revid": 329110052, "user": "Michael Hardy", "parentid": 329109371, "size": 17776}, {"comment": "/* The basic inversion equation is lacking */", "sha1": "b822269bea19b7c0e33bd3e5ec11ab1fed86bbbf", "timestamp": "2009-12-01T21:02:32Z", "userid": 4626, "revid": 329109371, "user": "Michael Hardy", "parentid": 329109327, "size": 17462}, {"comment": "/* The basic inversion equation is lacking */", "sha1": "b26110013344223b0177ded1a002b6619781b382", "timestamp": "2009-12-01T21:02:17Z", "userid": 4626, "revid": 329109327, "user": "Michael Hardy", "parentid": 329095684, "size": 17454}, {"comment": "/* The basic inversion equation is lacking */ new section", "sha1": "d6e65e4b10299ee35b6f7c9a77350b3dd9cf9466", "timestamp": "2009-12-01T19:51:32Z", "userid": 0, "revid": 329095684, "anon": "", "user": "190.24.55.241", "parentid": 313548444, "size": 17051}, {"comment": "/* Terminology standard */ new section", "sha1": "48ef194efae58b68f91e7db20ba8e4e235a95604", "timestamp": "2009-09-13T10:51:39Z", "userid": 433687, "revid": 313548444, "user": "RDBury", "parentid": 313511793, "size": 16334}, {"comment": "/* Orthogonality of spheres? */ Response", "sha1": "cd5d6d93f842cccfc72121cdd713b28e001d471c", "timestamp": "2009-09-13T05:18:41Z", "userid": 433687, "revid": 313511793, "user": "RDBury", "parentid": 305699507, "size": 15732}, {"comment": "/* reciprocation and M\u00f6bius-Group */ missing subscripts", "sha1": "c6479202ea5a685667bb13f9091e643b33a50f96", "timestamp": "2009-08-02T21:30:19Z", "userid": 92899, "revid": 305699507, "user": "Rgdboer", "parentid": 305696246, "size": 15497}, {"comment": "/* Proposed removal of a link */ one down", "sha1": "2bc63acde97ad46433da9781b81c4abaa67c48e3", "timestamp": "2009-08-02T21:07:56Z", "userid": 92899, "revid": 305696246, "user": "Rgdboer", "parentid": 305616997, "size": 15130}, {"comment": "", "sha1": "4f4fb8d2e1e80d34c9ed2fa67592b76d4ff18c44", "timestamp": "2009-08-02T11:27:29Z", "userid": 10239742, "revid": 305616997, "user": "Jbogaarts", "parentid": 280821326, "size": 14933}, {"comment": "/* a small mistake about notation. */", "sha1": "cdee8581a00448a80c3fc6f0064dabeadd53cdb3", "timestamp": "2009-03-31T08:04:00Z", "userid": 8359592, "revid": 280821326, "user": "Liuyifourfire", "parentid": 280820858, "size": 14694}, {"comment": "/* a small mistake about notation. */", "sha1": "9fad28f727cd9f61179ceaeebdaf491a39815afa", "timestamp": "2009-03-31T07:58:34Z", "userid": 0, "revid": 280820858, "anon": "", "user": "121.205.179.58", "parentid": 280820798, "size": 15349}, {"comment": "/* a small mistake about notation. */ new section", "sha1": "1177bf8a1292bf7dd4857d23ea7458a05f1d7d71", "timestamp": "2009-03-31T07:58:00Z", "userid": 0, "revid": 280820798, "anon": "", "user": "121.205.179.58", "parentid": 253928452, "size": 15350}, {"comment": "C class rating is deprecated", "sha1": "855f83e0446809789b07c8ffcd5316523b9d94a2", "timestamp": "2008-11-25T02:59:59Z", "userid": 558477, "revid": 253928452, "user": "RayAYang", "parentid": 249724696, "size": 14391}, {"comment": "/* reciprocation and M\u00f6bius-Group */ reiteration", "sha1": "1431ebd2e7dff9d79711be5a545dccb72609af2f", "timestamp": "2008-11-04T21:12:10Z", "userid": 92899, "revid": 249724696, "user": "Rgdboer", "parentid": 249601416, "size": 14387}, {"comment": "", "sha1": "90ead0112c12bf7e8acdb1cac8e15758382bf5ca", "timestamp": "2008-11-04T07:36:19Z", "userid": 8237832, "revid": 249601416, "user": "Nesta 4iver", "parentid": 249599394, "size": 13986}, {"comment": "/* reciprocation and M\u00f6bius-Group */ new section", "sha1": "146dc9ece87b024647677f922c95d7ce55aed5a1", "timestamp": "2008-11-04T07:15:32Z", "userid": 8237832, "revid": 249599394, "user": "Nesta 4iver", "parentid": 231751983, "size": 13974}, {"comment": "C-class", "sha1": "592a619bee4e57d06382e657070bff3432699a4e", "timestamp": "2008-08-13T20:22:34Z", "userid": 258000, "revid": 231751983, "user": "King of Hearts", "parentid": 224467696, "size": 13368}, {"comment": "Maths rating tag", "sha1": "b4ae36fabe350222601cefa8f6d5be57a938442d", "timestamp": "2008-07-08T23:39:14Z", "userid": 433687, "revid": 224467696, "user": "RDBury", "parentid": 216747259, "size": 13372}, {"comment": "/* Split Inversion (geometry) to Circle inversion and Circular transformation */", "sha1": "9779cd4c9495749a23982567439a33573353ba23", "timestamp": "2008-06-03T00:55:22Z", "userid": 454640, "revid": 216747259, "user": "Melchoir", "parentid": 216708913, "size": 13302}, {"comment": "/* Split Inversion (geometry) to Circle inversion and Circular transformation */", "sha1": "3eec4094e71c223dfc5490bf9a8060177ad85e67", "timestamp": "2008-06-02T21:19:27Z", "userid": 92899, "revid": 216708913, "user": "Rgdboer", "parentid": 216698334, "size": 13040}, {"comment": "moved [[Talk:Inversion (geometry)]] to [[Talk:Inversive geometry]] over redirect: common subject heading", "sha1": "05d73c522101e36ca72fce40f543cf2e9de4013b", "timestamp": "2008-06-02T20:31:14Z", "userid": 92899, "revid": 216698334, "user": "Rgdboer", "parentid": 216463941, "size": 12773}, {"comment": "/* Split Inversion (geometry) to Circle inversion and Circular transformation */", "sha1": "05d73c522101e36ca72fce40f543cf2e9de4013b", "timestamp": "2008-06-01T19:51:00Z", "userid": 454640, "revid": 216463941, "user": "Melchoir", "parentid": 215907851, "size": 12773}, {"comment": "/* Orthogonality of spheres? */ new section", "sha1": "dabee84c7a4196c48b7d6ffc238b9cc793307218", "timestamp": "2008-05-30T06:13:07Z", "userid": 1559980, "revid": 215907851, "user": "LachlanA", "parentid": 215192105, "size": 12660}, {"comment": "/* Split Inversion (geometry) to Circle inversion and Circular transformation */ suggest Inversive Geometry", "sha1": "dc10daa95783c2d831d5472d78ce6e733b383ea2", "timestamp": "2008-05-27T02:56:56Z", "userid": 92899, "revid": 215192105, "user": "Rgdboer", "parentid": 215099160, "size": 12272}, {"comment": "/* Not mathematical rigour */", "sha1": "86851f2fe338672e8a14a0cc12e7a92200d31533", "timestamp": "2008-05-26T18:24:49Z", "userid": 1559980, "revid": 215099160, "user": "LachlanA", "parentid": 214722822, "size": 11925}, {"comment": "/* Split Inversion (geometry) to Circle inversion and Circular transformation */", "sha1": "b49b7951eb8143f66968d1d0ad6b26398a778940", "timestamp": "2008-05-24T23:46:04Z", "userid": 454640, "revid": 214722822, "user": "Melchoir", "parentid": 214682152, "size": 11021}, {"comment": "/* Split Inversion (geometry) to Circle inversion and Circular transformation */ demur", "sha1": "bb4515ce01a03a22bdca1b318761013b0fbe1ab2", "timestamp": "2008-05-24T19:41:35Z", "userid": 92899, "revid": 214682152, "user": "Rgdboer", "parentid": 214546410, "size": 10051}, {"comment": "/* Split Inversion (geometry) to Circle inversion and Circular transformation */", "sha1": "c46114c49286c864f9ac3447893477d222a61f35", "timestamp": "2008-05-24T01:44:46Z", "userid": 454640, "revid": 214546410, "user": "Melchoir", "parentid": 214370043, "size": 9020}, {"comment": "/* Split Inversion (geometry) to Circle inversion and Circular transformation */ new section", "sha1": "e2c4f43dbb042b4dd7a1a2be74d7ce61509d1fea", "timestamp": "2008-05-23T06:46:53Z", "userid": 454640, "revid": 214370043, "user": "Melchoir", "parentid": 207628423, "size": 8849}, {"comment": "/* Not mathematical rigour */ new section", "sha1": "e26fa37061cec6ccf0630fe8c3d89bcc619a3741", "timestamp": "2008-04-23T15:41:56Z", "userid": 6624236, "revid": 207628423, "user": "Niarch", "parentid": 120809173, "size": 7588}, {"comment": "Too narrow", "sha1": "5220921f735e0680cb2c4f97ffa43e63feee0f03", "timestamp": "2007-04-06T19:56:07Z", "userid": 287933, "revid": 120809173, "user": "KSmrq", "parentid": 64973120, "size": 5919}, {"comment": "moved [[Talk:Inversive geometry]] to [[Talk:Inversion (geometry)]]: better name", "sha1": "e37c072eb4b21dc8260f0eb21a89adf094693102", "timestamp": "2006-07-21T03:34:05Z", "userid": 153314, "revid": 64973120, "user": "Oleg Alexandrov", "parentid": 64378306, "size": 5652}, {"comment": "/* relation to mobius trans */", "sha1": "e37c072eb4b21dc8260f0eb21a89adf094693102", "timestamp": "2006-07-18T00:10:49Z", "userid": 29920, "revid": 64378306, "user": "P0lyglut", "parentid": 64378160, "size": 5652}, {"comment": "/* relation to mobius trans */", "sha1": "d8ae93ad95669b774491eb58acc5e11eabc8449b", "timestamp": "2006-07-18T00:09:48Z", "userid": 29920, "revid": 64378160, "user": "P0lyglut", "parentid": 64362073, "size": 5653}, {"comment": "/* Inversions in three dimensions */", "sha1": "199de22a0276fca6981ec2cbbc5fa0d6632fa87c", "timestamp": "2006-07-17T22:17:05Z", "userid": 29920, "revid": 64362073, "user": "P0lyglut", "parentid": 64129459, "size": 5651}, {"comment": "/* critical but missing topics: sph inv, mob trans, stereo proj */ copyedit", "sha1": "d63b8522f79ad61ca0cbdf52f94989f4e266bb6b", "timestamp": "2006-07-16T16:04:11Z", "userid": 153314, "revid": 64129459, "user": "Oleg Alexandrov", "parentid": 63971685, "size": 5318}, {"comment": "/* critical but missing topics: sph inv, mob trans, stereo proj */", "sha1": "c7afbff88c11a5893ef802b89329678127fe476c", "timestamp": "2006-07-15T16:22:18Z", "userid": 29920, "revid": 63971685, "user": "P0lyglut", "parentid": 63970523, "size": 5158}, {"comment": "/* critical but missing topics: sph inv, mob trans, stereo proj */", "sha1": "4a1a81e4e8d60d3848f7adff86e0b5c46a5f400b", "timestamp": "2006-07-15T16:13:43Z", "userid": 29920, "revid": 63970523, "user": "P0lyglut", "parentid": 63970468, "size": 4654}, {"comment": "/* critical but missing topics: sph inv, mob trans, stereo proj */", "sha1": "701a612ef9e12458955dc17079c300b332f05fe4", "timestamp": "2006-07-15T16:13:27Z", "userid": 29920, "revid": 63970468, "user": "P0lyglut", "parentid": 63969931, "size": 4655}, {"comment": "/* critical but missing topics in this article */", "sha1": "dc7f84d8e87ca3207240d3c876c53ecbea65e181", "timestamp": "2006-07-15T16:09:53Z", "userid": 29920, "revid": 63969931, "user": "P0lyglut", "parentid": 63969827, "size": 4574}, {"comment": "critical but missing topics in this article", "sha1": "a31cdfa0accc678bc1a0b73ed36849c802cf8245", "timestamp": "2006-07-15T16:09:14Z", "userid": 29920, "revid": 63969827, "user": "P0lyglut", "parentid": 51585966, "size": 4557}, {"comment": "Anti-deSitter", "sha1": "6292e8726fe7dca7d479780042c38431a3d729c5", "timestamp": "2006-05-04T21:57:16Z", "userid": 39844, "revid": 51585966, "user": "Gene Ward Smith", "parentid": 51370401, "size": 3275}, {"comment": "==QBAsic==, agree", "sha1": "b0ec0ade29a7617a8f9d4678db6448d1edc1adda", "timestamp": "2006-05-03T14:53:31Z", "userid": 153314, "revid": 51370401, "user": "Oleg Alexandrov", "parentid": 51333375, "size": 2853}, {"comment": "", "sha1": "0a757238d84d6b9c82b018f4cd69fdaaaf14b448", "timestamp": "2006-05-03T07:51:07Z", "userid": 39844, "revid": 51333375, "user": "Gene Ward Smith", "parentid": 25736416, "size": 2455}, {"comment": "/* Change to the introduction */", "sha1": "e7d08cc80e77fa4361d02eb4beef078e00cce0c8", "timestamp": "2005-10-17T13:04:06Z", "userid": 153314, "revid": 25736416, "user": "Oleg Alexandrov", "parentid": 25736380, "size": 2181}, {"comment": "==Change to the introduction==", "sha1": "b46f9ded92e225d43525dfa0003701c10a96c000", "timestamp": "2005-10-17T13:03:27Z", "userid": 153314, "revid": 25736380, "user": "Oleg Alexandrov", "parentid": 25069716, "size": 2182}, {"comment": "/* My reversions */", "sha1": "ce0654c904ad6efb0cecd3ee6dcd4d1d73fc7875", "timestamp": "2005-10-08T17:22:08Z", "userid": 153314, "revid": 25069716, "user": "Oleg Alexandrov", "parentid": 25069619, "size": 1604}, {"comment": "My reversions", "sha1": "0fafab686c4e494342dca1f4fb4ec7815c8cb7a8", "timestamp": "2005-10-08T17:20:38Z", "userid": 153314, "revid": 25069619, "user": "Oleg Alexandrov", "parentid": 17080602, "size": 1512}, {"comment": "", "sha1": "5d655bc12e9e1c98443eec2702ec4ccc365af63f", "timestamp": "2005-01-01T05:31:51Z", "userid": 18901, "revid": 17080602, "user": "Phys", "parentid": 0, "size": 121}]}