{"lastrevid": 640140336, "pageid": 23919, "canonicalurl": "http://en.wikipedia.org/wiki/Talk:Platonic_solid", "links": [{"ns": 0, "title": "24-cell"}, {"ns": 0, "title": "Archimedean solid"}, {"ns": 0, "title": "Carved Stone Balls"}, {"ns": 0, "title": "Classical element"}, {"ns": 0, "title": "Combinatorics"}, {"ns": 0, "title": "Convex set"}, {"ns": 0, "title": "Conway polyhedron notation"}, {"ns": 0, "title": "Cube"}, {"ns": 0, "title": "Descartes"}, {"ns": 0, "title": "Dodecahedron"}, {"ns": 0, "title": "Dual polyhedron"}, {"ns": 0, "title": "Electron shell model"}, {"ns": 0, "title": "Euler"}, {"ns": 0, "title": "Flower of Life"}, {"ns": 0, "title": "Fluorite"}, {"ns": 0, "title": "GIF"}, {"ns": 0, "title": "Hexagon"}, {"ns": 0, "title": "Hexahedron"}, {"ns": 0, "title": "Icosahedron"}, {"ns": 0, "title": "Leonardo da Vinci"}, {"ns": 0, "title": "Leonhard Euler"}, {"ns": 0, "title": "Mathematics"}, {"ns": 0, "title": "Octahedron"}, {"ns": 0, "title": "Platonic solid"}, {"ns": 0, "title": "Platonic solids"}, {"ns": 0, "title": "Polyhedron"}, {"ns": 0, "title": "Rectification (geometry)"}, {"ns": 0, "title": "Rectified 16-cell"}, {"ns": 0, "title": "Regular polyhedron"}, {"ns": 0, "title": "Sacred geometry"}, {"ns": 0, "title": "Similarity (geometry)"}, {"ns": 0, "title": "Tessellation"}, {"ns": 0, "title": "Tetrahedron"}, {"ns": 0, "title": "Truncated icosahedron"}, {"ns": 0, "title": "Truncated tetrahedron"}, {"ns": 0, "title": "Uniform polyhedron"}], "title": "Talk:Platonic solid", "editurl": "http://en.wikipedia.org/w/index.php?title=Talk:Platonic_solid&action=edit", "contentmodel": "wikitext", "length": 40859, "pagelanguage": "en", "touched": "2015-04-18T10:10:25Z", "ns": 1, "fullurl": "http://en.wikipedia.org/wiki/Talk:Platonic_solid", "categories": [{"ns": 14, "title": "Category:B-Class mathematics articles"}, {"ns": 14, "title": "Category:Featured articles on Mathematics Portal"}, {"ns": 14, "title": "Category:Frequently viewed mathematics articles"}, {"ns": 14, "title": "Category:High-Priority mathematics articles"}, {"ns": 14, "title": "Category:Mathematics articles related to geometry"}], "revisions": [{"comment": "/* Proposals of more data in the article */", "sha1": "ba9ae04ad38dfe13db513a352ab39a4bebb447e2", "timestamp": "2014-12-29T20:46:23Z", "userid": 63601, "revid": 640140336, "user": "Tomruen", "parentid": 640140301, "size": 40859}, {"comment": "/* Proposals of more data in the article */", "sha1": "166815ecb0918bd5e01cc0c6a581f4601ab2af84", "timestamp": "2014-12-29T20:46:05Z", "userid": 63601, "revid": 640140301, "user": "Tomruen", "parentid": 640134882, "size": 40813}, {"comment": "/* Proposals of more data in the article */", "sha1": "4e9c415a39f6a0655dcf02435aa42d5f74a490b0", "timestamp": "2014-12-29T20:07:06Z", "userid": 63601, "revid": 640134882, "user": "Tomruen", "parentid": 640085151, "size": 40743}, {"comment": "/* Proposals of more data in the article */", "sha1": "e6527c1afdbeff9c4999708b2f3081be72eb3d29", "timestamp": "2014-12-29T12:50:27Z", "userid": 0, "revid": 640085151, "anon": "", "user": "31.11.242.188", "parentid": 640084583, "size": 40755}, {"comment": "/* Proposals of more date in the article */", "sha1": "e4e61e4a23562296dc5229b783f5e54d35b3296a", "timestamp": "2014-12-29T12:44:28Z", "userid": 0, "revid": 640084583, "anon": "", "user": "31.11.242.188", "parentid": 640083943, "size": 40687}, {"comment": "/* Proposals of more date in the article */ new section", "sha1": "d99bce387166a63ec54415fcb0b64268012832cb", "timestamp": "2014-12-29T12:37:48Z", "userid": 0, "revid": 640083943, "anon": "", "user": "31.11.242.188", "parentid": 588577217, "size": 40687}, {"comment": "/* Geodesic Sphere */ triangles", "sha1": "3042e78b75ab85241f426a7100f8417844d63a33", "timestamp": "2013-12-31T21:37:15Z", "userid": 2051880, "revid": 588577217, "user": "David Eppstein", "parentid": 588576959, "size": 39256}, {"comment": "r", "sha1": "fb35034203d52467b564e0dc1752f3d77ed94ce1", "timestamp": "2013-12-31T21:34:50Z", "userid": 2051880, "revid": 588576959, "user": "David Eppstein", "parentid": 588568233, "size": 39069}, {"comment": "/* Geodesic Sphere */", "sha1": "a7be7fd34b23302442c51fa9385ebc8ba369b5d2", "timestamp": "2013-12-31T20:16:59Z", "userid": 3161245, "revid": 588568233, "user": "DarkShroom", "parentid": 588567943, "size": 38704}, {"comment": "Signing comment by [[User:DarkShroom|DarkShroom]] - \"\"", "sha1": "681ce20d4414df7c1c6b9a1e29eca2325514d3ee", "timestamp": "2013-12-31T20:14:09Z", "userid": 4936590, "revid": 588567943, "user": "SineBot", "parentid": 588567792, "size": 38927}, {"comment": "", "sha1": "00493b1ca6aa152d6f1db2a249cc52e05bc62913", "timestamp": "2013-12-31T20:12:50Z", "userid": 3161245, "revid": 588567792, "user": "DarkShroom", "parentid": 570308702, "size": 38611}, {"comment": "/* Intro section */ proposed addition to intro", "sha1": "2819303c76400260f7ab85b1ef205afd71ec79a8", "timestamp": "2013-08-26T20:33:07Z", "userid": 0, "revid": 570308702, "anon": "", "user": "75.150.168.6", "parentid": 547264831, "size": 38205}, {"comment": "/* need answer */ response to IP editor", "sha1": "331220f3d40d1978ad43a54839abfbd76a81271a", "timestamp": "2013-03-27T14:03:02Z", "userid": 346060, "revid": 547264831, "user": "Mgnbar", "parentid": 547227819, "size": 37943}, {"comment": "Signing comment by [[Special:Contributions/111.194.118.16|111.194.118.16]] - \"/* need answer */ new section\"", "sha1": "5e22f5ab10eae416087c6bf8b78f39be76245637", "timestamp": "2013-03-27T09:44:12Z", "userid": 4936590, "revid": 547227819, "user": "SineBot", "parentid": 547227686, "size": 37646}, {"comment": "/* need answer */ new section", "sha1": "d33e217eef2522213491e20f2d399117953fa680", "timestamp": "2013-03-27T09:42:59Z", "userid": 0, "revid": 547227686, "anon": "", "user": "111.194.118.16", "parentid": 514962024, "size": 37343}, {"comment": "Banner clean up using [[Project:AWB|AWB]] (8436)", "sha1": "a3b9c1c473c5908e24422958776115b919328a8f", "timestamp": "2012-09-28T08:12:21Z", "userid": 7328338, "revid": 514962024, "user": "Yobot", "parentid": 506660865, "size": 37248}, {"comment": "Using maths rating template for [[:Category:Featured articles on Mathematics Portal]] instead of manual addition.", "sha1": "67551d7bab7421dea4b49e2155ca6fc80de3ed4e", "timestamp": "2012-08-10T02:12:40Z", "userid": 775188, "revid": 506660865, "user": "Nat2", "parentid": 487918651, "size": 37247}, {"comment": "/* Intro section */", "sha1": "db7d75f29b7396ac618bc42f6a092727c30784f6", "timestamp": "2012-04-17T23:49:32Z", "userid": 445466, "revid": 487918651, "user": "Mangoe", "parentid": 487915921, "size": 37289}, {"comment": "/* Intro section */ succinct", "sha1": "a1fcc02ad2ebea6fd812d5a79ca129de4c6a8361", "timestamp": "2012-04-17T23:26:34Z", "userid": 346060, "revid": 487915921, "user": "Mgnbar", "parentid": 487864432, "size": 37195}, {"comment": "/* Intro section */ response to Mangoe", "sha1": "53078165689bce420866d0515fd10450bd62d8ea", "timestamp": "2012-04-17T17:29:15Z", "userid": 346060, "revid": 487864432, "user": "Mgnbar", "parentid": 487855362, "size": 36750}, {"comment": "/* Intro section */", "sha1": "3758dbdf09d4821e0231198e8ef85ba0bc5878e6", "timestamp": "2012-04-17T16:28:57Z", "userid": 445466, "revid": 487855362, "user": "Mangoe", "parentid": 487830230, "size": 36506}, {"comment": "/* Intro section */ trying a less technical version", "sha1": "74149a3764f98b457db0adf3e87255ccad9710b5", "timestamp": "2012-04-17T13:24:03Z", "userid": 445466, "revid": 487830230, "user": "Mangoe", "parentid": 487821928, "size": 36308}, {"comment": "/* Intro section */ why are people refusing to form consensus?", "sha1": "9290d00998a51b25f43980f3a7aafc9850996c4f", "timestamp": "2012-04-17T12:15:16Z", "userid": 346060, "revid": 487821928, "user": "Mgnbar", "parentid": 487771434, "size": 36127}, {"comment": "/* Similarity classes */ okay, omit it", "sha1": "f0a4cacc8ad1dceaf5c2d3d455080fa10c71cd6b", "timestamp": "2012-04-17T02:34:57Z", "userid": 346060, "revid": 487771434, "user": "Mgnbar", "parentid": 487766678, "size": 35857}, {"comment": "/* Similarity classes */ can't we just leave the phrase out?", "sha1": "9495242c77c4f2376a2bfd0b18f6464e283da87f", "timestamp": "2012-04-17T01:50:16Z", "userid": 445466, "revid": 487766678, "user": "Mangoe", "parentid": 487746094, "size": 35563}, {"comment": "/* Similarity classes */ response to Mangoe", "sha1": "e603809ff19d40e36652464ca3f62e7b7c1d3684", "timestamp": "2012-04-16T22:48:17Z", "userid": 346060, "revid": 487746094, "user": "Mgnbar", "parentid": 487745627, "size": 35098}, {"comment": "", "sha1": "8f254f75eb11a6794f1b869e17aa1960140ca309", "timestamp": "2012-04-16T22:44:30Z", "userid": 445466, "revid": 487745627, "user": "Mangoe", "parentid": 487745573, "size": 34790}, {"comment": "/* Similarity classes */", "sha1": "faf4447a9f08c53f905b180491a2abb48e591902", "timestamp": "2012-04-16T22:44:01Z", "userid": 445466, "revid": 487745573, "user": "Mangoe", "parentid": 487728775, "size": 34736}, {"comment": "/* Intro section */ new section", "sha1": "cf204888d3c2a45709dfc7d75c1bcc4567547c84", "timestamp": "2012-04-16T20:50:21Z", "userid": 346060, "revid": 487728775, "user": "Mgnbar", "parentid": 484332622, "size": 34655}, {"comment": "/* Moon model */ new section", "sha1": "f33e42cd291631473a13b05a9089a64682042bf2", "timestamp": "2012-03-28T09:34:32Z", "userid": 15117005, "revid": 484332622, "user": "Ridcully Jack", "parentid": 482778763, "size": 33950}, {"comment": "Move [[Category:Featured articles on Mathematics Portal]] from article to talkpage per [[Wikipedia:Categories for discussion/Log/2012 March 12]] using [[Project:AWB|AWB]]", "sha1": "d37336ec46b11ae77e01f553aafa0581901514de", "timestamp": "2012-03-19T20:18:34Z", "userid": 32005, "revid": 482778763, "user": "Timrollpickering", "parentid": 465708161, "size": 33340}, {"comment": "/* Similarity classes */", "sha1": "c0ed3bd570c0ad57ebed51eb758219613934cf88", "timestamp": "2011-12-13T21:47:40Z", "userid": 11880536, "revid": 465708161, "user": "Chricho", "parentid": 465379660, "size": 33290}, {"comment": "/* Similarity classes */  reply", "sha1": "17cfc4c5447d1da4d271a3da8ba93fac3cf28bdb", "timestamp": "2011-12-12T00:40:58Z", "userid": 15117005, "revid": 465379660, "user": "Ridcully Jack", "parentid": 465178555, "size": 33096}, {"comment": "/* Similarity classes */ new section", "sha1": "5cfe9b02052316210f77351a9699a4dfc039cbc6", "timestamp": "2011-12-10T21:26:34Z", "userid": 346060, "revid": 465178555, "user": "Mgnbar", "parentid": 462296346, "size": 32938}, {"comment": "/* Duality, truncation, snubbing? */", "sha1": "9c13af1a586016a6d007f3046428a7da58fa72b5", "timestamp": "2011-11-24T19:00:21Z", "userid": 0, "revid": 462296346, "anon": "", "user": "68.173.113.106", "parentid": 462175404, "size": 32464}, {"comment": "/* Icosahedral water clusters */", "sha1": "54fd01c31248253703833872d147da8b8939bd19", "timestamp": "2011-11-23T22:57:24Z", "userid": 0, "revid": 462175404, "anon": "", "user": "68.173.113.106", "parentid": 462175362, "size": 32055}, {"comment": "/* Duality, truncation, snubbing? */", "sha1": "05e219f10d206e15b4766db22b26150513471382", "timestamp": "2011-11-23T22:57:08Z", "userid": 63601, "revid": 462175362, "user": "Tomruen", "parentid": 462174730, "size": 31867}, {"comment": "/* Duality, truncation, snubbing? */", "sha1": "8353cd39be4477ac80d909190b2dbdd1061c33db", "timestamp": "2011-11-23T22:52:16Z", "userid": 0, "revid": 462174730, "anon": "", "user": "68.173.113.106", "parentid": 462174626, "size": 31620}, {"comment": "m /* Duality, truncation, snubbing? */ Changed the position of the link.", "sha1": "8a82d3215a09084ab87207a20f746b2125846ca6", "timestamp": "2011-11-23T22:51:31Z", "userid": 0, "revid": 462174626, "anon": "", "user": "68.173.113.106", "parentid": 462174433, "size": 31620}, {"comment": "/* Duality, truncation, snubbing? */ NEW IMAGE", "sha1": "d35a6c67edb1fc7cb9d0e42855819a34925dbe43", "timestamp": "2011-11-23T22:50:09Z", "userid": 0, "revid": 462174433, "anon": "", "user": "68.173.113.106", "parentid": 462011907, "size": 32073}, {"comment": "/* external link missing */", "sha1": "fd8c667f2a2aca8e8188fa5da31cd0235ff81438", "timestamp": "2011-11-22T22:39:20Z", "userid": 0, "revid": 462011907, "anon": "", "user": "68.173.113.106", "parentid": 460460026, "size": 30912}, {"comment": "Signing comment by [[Special:Contributions/69.116.209.152|69.116.209.152]] - \"/* Level of Proof and supposed vandalism */\"", "sha1": "0ff52aaaeca41c2cd8bbea5706ce460990d9f4d1", "timestamp": "2011-11-13T16:40:52Z", "userid": 4936590, "revid": 460460026, "user": "SineBot", "parentid": 460459868, "size": 30612}, {"comment": "/* Level of Proof and supposed vandalism */", "sha1": "28a104b2662cdd8d132ef50de59809bac508991a", "timestamp": "2011-11-13T16:39:41Z", "userid": 0, "revid": 460459868, "anon": "", "user": "69.116.209.152", "parentid": 434174072, "size": 30306}, {"comment": "/* Duality, truncation, snubbing? */", "sha1": "8e02f3b683cf4b49b9c0c7c21442748454edc334", "timestamp": "2011-06-14T03:43:43Z", "userid": 63601, "revid": 434174072, "user": "Tomruen", "parentid": 434173813, "size": 30101}, {"comment": "", "sha1": "9967cde5a391c9e141b543e9e6ffaba7f8cc8229", "timestamp": "2011-06-14T03:41:03Z", "userid": 63601, "revid": 434173813, "user": "Tomruen", "parentid": 434171084, "size": 29933}, {"comment": "/* Duality, truncation, snubbing? */ new section", "sha1": "bda4796455cde8d8d3ff293b7a88fd006e5271b6", "timestamp": "2011-06-14T03:14:09Z", "userid": 4905094, "revid": 434171084, "user": "Qartar", "parentid": 433503907, "size": 29675}, {"comment": "/* 24-cell and hexagon */", "sha1": "a466448d3270c4181b3660f4bb4fbd759abbccb4", "timestamp": "2011-06-10T05:07:38Z", "userid": 63601, "revid": 433503907, "user": "Tomruen", "parentid": 433341896, "size": 29147}, {"comment": "/* 24-cell and hexagon */ new section", "sha1": "c5e9e5e0c83fcb47e4c0455b577bcdc50f6c6aa2", "timestamp": "2011-06-09T06:05:26Z", "userid": 609725, "revid": 433341896, "user": "Tamfang", "parentid": 412853448, "size": 29003}, {"comment": "/* sacred geometry */", "sha1": "1a1fafb7e103cdf7ca372af23e6a89052c9c8017", "timestamp": "2011-02-09T04:05:27Z", "userid": 63601, "revid": 412853448, "user": "Tomruen", "parentid": 412850822, "size": 28665}, {"comment": "/* sacred geometry */", "sha1": "b32359a19d4149d4e5f028fafd908412f4cf2153", "timestamp": "2011-02-09T03:43:04Z", "userid": 21047, "revid": 412850822, "user": "AnonMoos", "parentid": 412798484, "size": 28661}, {"comment": "/* sacred geometry */ new section", "sha1": "3769ec7867ca989c01ed1f4843c1badd8f01f022", "timestamp": "2011-02-08T22:14:28Z", "userid": 863221, "revid": 412798484, "user": "Jeiki Rebirth", "parentid": 396965437, "size": 28520}, {"comment": "/* Removal of \"medieval\" elements, why? */ response to anonymous", "sha1": "bfc13ab2afb024bc4030d7d76841de3d97c3c849", "timestamp": "2010-11-15T19:42:41Z", "userid": 346060, "revid": 396965437, "user": "Mgnbar", "parentid": 396824209, "size": 28318}, {"comment": "Signing comment by [[Special:Contributions/188.58.27.116|188.58.27.116]] - \"/* Removal of \"medieval\" elements, why? */\"", "sha1": "4c05901d560f68f764571ef4d7ac7f4b0a8835c1", "timestamp": "2010-11-15T02:02:27Z", "userid": 4936590, "revid": 396824209, "user": "SineBot", "parentid": 396824033, "size": 27531}, {"comment": "/* Removal of \"medieval\" elements, why? */", "sha1": "c35ac434c0f0c27967299f2ee854cbe1a9c48e39", "timestamp": "2010-11-15T02:01:21Z", "userid": 0, "revid": 396824033, "anon": "", "user": "188.58.27.116", "parentid": 396407067, "size": 27230}, {"comment": "/* Removal of \"medieval\" elements, why? */", "sha1": "f56ab5bdc9d5a034480e17d87c594cb81ad4ab26", "timestamp": "2010-11-12T23:12:49Z", "userid": 609725, "revid": 396407067, "user": "Tamfang", "parentid": 396402516, "size": 26410}, {"comment": "/* Removal of \"medieval\" elements, why? */ move elemental labels to lead?", "sha1": "faf7ac1676557c9899bcc27358623524be34f3de", "timestamp": "2010-11-12T22:44:09Z", "userid": 346060, "revid": 396402516, "user": "Mgnbar", "parentid": 396371738, "size": 26231}, {"comment": "/* Removal of \"medieval\" elements, why? */", "sha1": "2da3e44c14fad8d2556715b7823930cad7d997b4", "timestamp": "2010-11-12T19:40:19Z", "userid": 609725, "revid": 396371738, "user": "Tamfang", "parentid": 396365368, "size": 25980}, {"comment": "Signing comment by [[Special:Contributions/188.59.189.29|188.59.189.29]] - \"\"", "sha1": "669201a205b49cf2d528df9c3dd27c8b90c9ebca", "timestamp": "2010-11-12T18:59:23Z", "userid": 4936590, "revid": 396365368, "user": "SineBot", "parentid": 396365157, "size": 25760}, {"comment": "", "sha1": "cd98bed7ee1ffe455be07ca51d311cb3df7e540e", "timestamp": "2010-11-12T18:58:05Z", "userid": 0, "revid": 396365157, "anon": "", "user": "188.59.189.29", "parentid": 369248213, "size": 25459}, {"comment": "/* Euler formula */ new section", "sha1": "d0dea19153b267920afe2a88e6b60094c121054c", "timestamp": "2010-06-20T22:15:40Z", "userid": 609725, "revid": 369248213, "user": "Tamfang", "parentid": 366541050, "size": 24452}, {"comment": "headers", "sha1": "4e113f3f64bc1b6183fed72e3cfa5cd860346d04", "timestamp": "2010-06-07T11:23:52Z", "userid": 545027, "revid": 366541050, "user": "Thumperward", "parentid": 362044401, "size": 23947}, {"comment": "[[Help:Reverting|Reverted]] edits by [[Special:Contributions/Tamfang|Tamfang]] ([[User talk:Tamfang|talk]]) to last version by Tetracube", "sha1": "34e08c27d3f7de79fb559437f6ac8fcc652cba15", "timestamp": "2010-05-14T06:35:20Z", "userid": 609725, "revid": 362044401, "user": "Tamfang", "parentid": 362044355, "size": 23897}, {"comment": "/* dual or polar (see dual) */", "sha1": "5ee6f6520b6160c2d0ed187bddeb08235a7bbe67", "timestamp": "2010-05-14T06:34:59Z", "userid": 609725, "revid": 362044355, "user": "Tamfang", "parentid": 361944056, "size": 24046}, {"comment": "/* dual or polar (see dual) */", "sha1": "34e08c27d3f7de79fb559437f6ac8fcc652cba15", "timestamp": "2010-05-13T19:25:09Z", "userid": 356300, "revid": 361944056, "user": "Tetracube", "parentid": 361927403, "size": 23897}, {"comment": "/* dual or polar (see dual) */", "sha1": "aa7829c6f52d72b0295b9725cdda2a4ab8b3138b", "timestamp": "2010-05-13T17:53:44Z", "userid": 609725, "revid": 361927403, "user": "Tamfang", "parentid": 361927281, "size": 23656}, {"comment": "/* dual or polar (see dual) */ new section", "sha1": "f866008535a87932a1f08fe7d7cf14ffe27fac59", "timestamp": "2010-05-13T17:53:04Z", "userid": 609725, "revid": 361927281, "user": "Tamfang", "parentid": 346949584, "size": 23657}, {"comment": "Class = B, lack of inline sites, references lack page numbers where needed, not a potential GA candidate. Importance = high, highly viewed but not a fundamental subject.", "sha1": "6396c3efd315a84039ab27050801d0440934fc63", "timestamp": "2010-02-28T20:49:26Z", "userid": 433687, "revid": 346949584, "user": "RDBury", "parentid": 343172195, "size": 22897}, {"comment": "/* Definition */ response to JohnWheater", "sha1": "12a0c9655746ed613388fc8450beb3a581cd591f", "timestamp": "2010-02-10T16:25:34Z", "userid": 346060, "revid": 343172195, "user": "Mgnbar", "parentid": 343137722, "size": 22915}, {"comment": "/* Definition */", "sha1": "b0f0beaef3d1797269c5a1833c8ba3561ae59b7f", "timestamp": "2010-02-10T12:05:16Z", "userid": 612921, "revid": 343137722, "user": "JohnWheater", "parentid": 343133250, "size": 20370}, {"comment": "/* Plato's categorisation of the dodecahedron */", "sha1": "8d6349556741a3913b3470242c8a3886db8d1602", "timestamp": "2010-02-10T11:20:47Z", "userid": 612921, "revid": 343133250, "user": "JohnWheater", "parentid": 318136291, "size": 19756}, {"comment": "response to 85.210.124.67", "sha1": "df0baa82886a8c97d8d6d04f103802fa0585d3b5", "timestamp": "2009-10-05T22:06:04Z", "userid": 346060, "revid": 318136291, "user": "Mgnbar", "parentid": 318101642, "size": 19182}, {"comment": "Signing comment by [[Special:Contributions/85.210.124.67|85.210.124.67]] - \"Added a comment\"", "sha1": "17798883d5ff5201efc81edb28e518980a6b4e68", "timestamp": "2009-10-05T19:04:54Z", "userid": 4936590, "revid": 318101642, "user": "SineBot", "parentid": 318101433, "size": 18943}, {"comment": "Added a comment", "sha1": "c4e5fb01ca666020d7da75fadf5ab50600a8c9fe", "timestamp": "2009-10-05T19:03:31Z", "userid": 0, "revid": 318101433, "anon": "", "user": "85.210.124.67", "parentid": 289183170, "size": 18644}, {"comment": "/* Category:Polyhedra vs. Category:Platonic solids  */ new section", "sha1": "031712359219d41610a58c9790637ab1a7b352fa", "timestamp": "2009-05-11T03:06:30Z", "userid": 2742851, "revid": 289183170, "user": "Robertgreer", "parentid": 256330679, "size": 18428}, {"comment": "", "sha1": "39496458091a6a7c0eb22bed57bf190b1e51165e", "timestamp": "2008-12-07T01:01:48Z", "userid": 8474979, "revid": 256330679, "user": "Nicholashopkinz", "parentid": 222833106, "size": 18178}, {"comment": "added Plato's categorisation of the dodecahedron", "sha1": "98530c8e4723b286df92301ebc7ce3a18cfbd4d0", "timestamp": "2008-07-01T09:54:06Z", "userid": 1807879, "revid": 222833106, "user": "Nazlfrag", "parentid": 212586229, "size": 17686}, {"comment": "Reverted edits by [[Special:Contributions/Yemins|Yemins]] ([[User talk:Yemins|talk]]) to last version by Tamfang", "sha1": "2d6e15aa07200bd44ec620cd885fc97acd0efa9d", "timestamp": "2008-05-15T12:11:37Z", "userid": 5947179, "revid": 212586229, "user": "Aitias", "parentid": 212586183, "size": 17206}, {"comment": "[[WP:AES|\u2190]]Blanked the page", "sha1": "da39a3ee5e6b4b0d3255bfef95601890afd80709", "timestamp": "2008-05-15T12:11:12Z", "userid": 7112041, "revid": 212586183, "user": "Yemins", "parentid": 212586135, "size": 0}, {"comment": "", "sha1": "7cc9c211d752681b11d25225ca2bca7a9195b940", "timestamp": "2008-05-15T12:10:51Z", "userid": 7112041, "revid": 212586135, "user": "Yemins", "parentid": 212585781, "size": 17274}, {"comment": "ddfh", "sha1": "7af6fd1b9444eda1813b0c1f7a52a87987245a6a", "timestamp": "2008-05-15T12:08:23Z", "userid": 7112041, "revid": 212585781, "user": "Yemins", "parentid": 199207446, "size": 17591}, {"comment": "/* Vandalism or just a faullty edit? */", "sha1": "2d6e15aa07200bd44ec620cd885fc97acd0efa9d", "timestamp": "2008-03-18T23:02:42Z", "userid": 609725, "revid": 199207446, "user": "Tamfang", "parentid": 198752256, "size": 17206}, {"comment": "/* Vandalism or just a faullty edit? */ new section", "sha1": "b1fd6ff080a2bb4ecfbc3d7f84ed90f3fad2dc00", "timestamp": "2008-03-17T00:39:40Z", "userid": 391998, "revid": 198752256, "user": "Tkrokli", "parentid": 196860311, "size": 17009}, {"comment": "Flagging as frequently viewed (bot, using LWB)", "sha1": "63c57430a0e6f10e3c3878afe49d16425cc04970", "timestamp": "2008-03-08T21:48:39Z", "userid": 3827324, "revid": 196860311, "user": "VeblenBot", "parentid": 193850829, "size": 16190}, {"comment": "/* Solid Angle */", "sha1": "c1f10df8c9073370147e888aa789bc4f079f3d3d", "timestamp": "2008-02-25T03:42:40Z", "userid": 5192039, "revid": 193850829, "user": "Firth m", "parentid": 193850559, "size": 16169}, {"comment": "/* Solid Angle */", "sha1": "0647013ece39943fefb6495ad60293f0ede10ea0", "timestamp": "2008-02-25T03:41:01Z", "userid": 0, "revid": 193850559, "anon": "", "user": "140.247.173.200", "parentid": 193850341, "size": 16209}, {"comment": "/* Solid Angle */", "sha1": "accf75ad295fc287b8ab706769771663894474c1", "timestamp": "2008-02-25T03:39:34Z", "userid": 0, "revid": 193850341, "anon": "", "user": "140.247.173.200", "parentid": 193850274, "size": 16351}, {"comment": "Signing comment by [[User:140.247.173.200|140.247.173.200]] - \"/* Solid Angle */ new section\"", "sha1": "7590d986c85fcfd80424df494c5858b024fdbe9e", "timestamp": "2008-02-25T03:39:13Z", "userid": 4936590, "revid": 193850274, "user": "SineBot", "parentid": 193850055, "size": 17371}, {"comment": "/* Solid Angle */ new section", "sha1": "498ed9dbb5e776190e7ae5148c913eddc2875f2e", "timestamp": "2008-02-25T03:37:44Z", "userid": 0, "revid": 193850055, "anon": "", "user": "140.247.173.200", "parentid": 193850007, "size": 17109}, {"comment": "Signing comment by [[User:140.247.173.200|140.247.173.200]] - \"/* Solid Angle */ new section\"", "sha1": "5340f8adf67ffefa70da0de9495bacf6ec6c25df", "timestamp": "2008-02-25T03:37:26Z", "userid": 4936590, "revid": 193850007, "user": "SineBot", "parentid": 193849787, "size": 16345}, {"comment": "/* Solid Angle */ new section", "sha1": "d33bcbff32470b73e423e29201518fb32639bc9c", "timestamp": "2008-02-25T03:35:59Z", "userid": 0, "revid": 193849787, "anon": "", "user": "140.247.173.200", "parentid": 189162924, "size": 16083}, {"comment": "rev nonsense comment", "sha1": "c71a3eca2e63cdd99f29a18afda82b2b22b11e75", "timestamp": "2008-02-05T01:24:30Z", "userid": 63601, "revid": 189162924, "user": "Tomruen", "parentid": 189110335, "size": 15323}, {"comment": "Signing comment by [[User:81.151.63.240|81.151.63.240]] - \"/* YAY */ new section\"", "sha1": "a40caf8a4cfd721ac1913baa276c3f859d59e511", "timestamp": "2008-02-04T21:21:34Z", "userid": 4936590, "revid": 189110335, "user": "SineBot", "parentid": 189109882, "size": 15687}, {"comment": "/* YAY */ new section", "sha1": "4b8b0a4a81b2dcba5e135b2e6e9e8943553476b9", "timestamp": "2008-02-04T21:19:42Z", "userid": 0, "revid": 189109882, "anon": "", "user": "81.151.63.240", "parentid": 175393276, "size": 15432}, {"comment": "/* History */", "sha1": "c71a3eca2e63cdd99f29a18afda82b2b22b11e75", "timestamp": "2007-12-03T02:22:17Z", "userid": 3083281, "revid": 175393276, "user": "Scorwin", "parentid": 175393001, "size": 15323}, {"comment": "/* History */ new section", "sha1": "ead32caf9278375cb9b95ea8c6b5d2a10d3df9d0", "timestamp": "2007-12-03T02:20:49Z", "userid": 3083281, "revid": 175393001, "user": "Scorwin", "parentid": 171826310, "size": 15499}, {"comment": "[[WP:UNDO|Undid]] revision 171818600 by [[Special:Contributions/66.229.38.255|66.229.38.255]] ([[User talk:66.229.38.255|talk]])", "sha1": "c71a3eca2e63cdd99f29a18afda82b2b22b11e75", "timestamp": "2007-11-16T04:39:07Z", "userid": 63601, "revid": 171826310, "user": "Tomruen", "parentid": 171818600, "size": 15323}, {"comment": "", "sha1": "0d2e4c053cd3a8197b6b5720885e5bee055b2c43", "timestamp": "2007-11-16T03:43:27Z", "userid": 0, "revid": 171818600, "anon": "", "user": "66.229.38.255", "parentid": 169658812, "size": 15459}, {"comment": "rev vandalism", "sha1": "c71a3eca2e63cdd99f29a18afda82b2b22b11e75", "timestamp": "2007-11-06T19:24:16Z", "userid": 63601, "revid": 169658812, "user": "Tomruen", "parentid": 169658207, "size": 15323}, {"comment": "", "sha1": "5a0435bbbd83760a45b183cfb72950878fe1c1e1", "timestamp": "2007-11-06T19:21:36Z", "userid": 0, "revid": 169658207, "anon": "", "user": "81.155.226.219", "parentid": 169657540, "size": 15396}, {"comment": "", "sha1": "b871ca763a546e122e12e1fa74f0db6984987e3e", "timestamp": "2007-11-06T19:18:41Z", "userid": 0, "revid": 169657540, "anon": "", "user": "81.155.226.219", "parentid": 165553485, "size": 15407}, {"comment": "Some comments on the symmetry groups", "sha1": "c71a3eca2e63cdd99f29a18afda82b2b22b11e75", "timestamp": "2007-10-19T02:57:39Z", "userid": 0, "revid": 165553485, "anon": "", "user": "24.200.80.227", "parentid": 131785903, "size": 15323}, {"comment": "Add maths rating with importance and field  using [[Project:AWB|AWB]]", "sha1": "2f5a5b89d88821204a759025ec05a2b05ff1f90c", "timestamp": "2007-05-18T14:56:34Z", "userid": 3483166, "revid": 131785903, "user": "Geometry guy", "parentid": 131745113, "size": 14827}, {"comment": "/* Level of Proof and supposed vandalism */", "sha1": "65bb880ce33d58acd58c0386a4c0fca89a339316", "timestamp": "2007-05-18T10:08:45Z", "userid": 1382292, "revid": 131745113, "user": "Rosser1954", "parentid": 131744915, "size": 14742}, {"comment": "", "sha1": "78969035143eb2e254b50d635b7328d862eb5847", "timestamp": "2007-05-18T10:07:12Z", "userid": 1382292, "revid": 131744915, "user": "Rosser1954", "parentid": 131551112, "size": 14658}, {"comment": "/* Level of Proof and supposed vandalism */ response to Rosser1954", "sha1": "2a25f98a3efc463ba8820d50f3cc629f254effd8", "timestamp": "2007-05-17T15:07:42Z", "userid": 346060, "revid": 131551112, "user": "Mgnbar", "parentid": 131520641, "size": 14647}, {"comment": "/* Saving '''Animations''' for powerpoint */", "sha1": "22ec8f1028896a54e409933c29fb0a3cbc244911", "timestamp": "2007-05-17T12:06:31Z", "userid": 1382292, "revid": 131520641, "user": "Rosser1954", "parentid": 123724755, "size": 13691}, {"comment": "/* Saving '''Animations''' for powerpoint */", "sha1": "212bd859d964899ce4224c507e343148ec5d5b8d", "timestamp": "2007-04-18T04:09:13Z", "userid": 1739571, "revid": 123724755, "user": "Ags412", "parentid": 123703243, "size": 12880}, {"comment": "/* Saving '''Animations''' for powerpoint */", "sha1": "6f633964d756af3de7874b28201b679064ec10c3", "timestamp": "2007-04-18T02:13:29Z", "userid": 63601, "revid": 123703243, "user": "Tomruen", "parentid": 123702774, "size": 12554}, {"comment": "", "sha1": "29dd3953680957087b106b4877efa5f199c5a941", "timestamp": "2007-04-18T02:10:46Z", "userid": 0, "revid": 123702774, "anon": "", "user": "69.150.181.225", "parentid": 119117502, "size": 12433}, {"comment": "/* Saving '''Animations''' for powerpoint */", "sha1": "cb67c15b118557834c48cd4f33787539222f0ec4", "timestamp": "2007-03-30T20:20:22Z", "userid": 1739571, "revid": 119117502, "user": "Ags412", "parentid": 119117188, "size": 12162}, {"comment": "/* Saving images for powerpoint */", "sha1": "1acba32aa2b9de3b84f62a581023d77fc61a353a", "timestamp": "2007-03-30T20:19:06Z", "userid": 1739571, "revid": 119117188, "user": "Ags412", "parentid": 118944475, "size": 11880}, {"comment": "/* Saving images for powerpoint */", "sha1": "7d205cc38bce564e18a30367cec8744163fc1315", "timestamp": "2007-03-30T02:29:21Z", "userid": 63601, "revid": 118944475, "user": "Tomruen", "parentid": 118944010, "size": 11870}, {"comment": "Saving images for powerpoint", "sha1": "46472ed7539b3301d22258a57cc0adc78c52c148", "timestamp": "2007-03-30T02:26:59Z", "userid": 63601, "revid": 118944010, "user": "Tomruen", "parentid": 118895911, "size": 11602}, {"comment": "", "sha1": "925e448304f94c2a093557905654e420beeab5e5", "timestamp": "2007-03-29T22:34:02Z", "userid": 0, "revid": 118895911, "anon": "", "user": "159.91.19.3", "parentid": 96914587, "size": 11243}, {"comment": "/* Icosahedral water clusters */", "sha1": "1c5b1bec57c14d6067cf12ded839e9490e684b0a", "timestamp": "2006-12-28T11:06:45Z", "userid": 1287765, "revid": 96914587, "user": "Sloth monkey", "parentid": 96914562, "size": 11024}, {"comment": "/* Icosahedral water clusters */", "sha1": "5d3d90ccddea19ec019652e1bfcce6d960c689bb", "timestamp": "2006-12-28T11:06:24Z", "userid": 1287765, "revid": 96914562, "user": "Sloth monkey", "parentid": 96914540, "size": 11025}, {"comment": "", "sha1": "d8b14341af271080323742e16987053ee13e304d", "timestamp": "2006-12-28T11:06:08Z", "userid": 1287765, "revid": 96914540, "user": "Sloth monkey", "parentid": 96907969, "size": 10959}, {"comment": "/* Leonardo da Vinci */", "sha1": "c5f4544fbf7b755398dca65a09d9134452ee2d96", "timestamp": "2006-12-28T09:47:33Z", "userid": 1287765, "revid": 96907969, "user": "Sloth monkey", "parentid": 96907910, "size": 10638}, {"comment": "", "sha1": "8228eee51ad2e408d3901579a2c4d79ed0f05de5", "timestamp": "2006-12-28T09:46:52Z", "userid": 1287765, "revid": 96907910, "user": "Sloth monkey", "parentid": 96340251, "size": 10572}, {"comment": "/* Regularity */", "sha1": "a53d989c645c72daa96bb238c80d868458cae98f", "timestamp": "2006-12-24T23:12:10Z", "userid": 116612, "revid": 96340251, "user": "Rsholmes", "parentid": 96026349, "size": 9398}, {"comment": "/* Regularity */", "sha1": "83966d5c56fe82253a1785166025393246ee4c80", "timestamp": "2006-12-23T01:45:25Z", "userid": 63601, "revid": 96026349, "user": "Tomruen", "parentid": 96023401, "size": 8233}, {"comment": "Regularity", "sha1": "0b78088fcf1839ec5edb5aa15fa1502a9edc4f2f", "timestamp": "2006-12-23T01:21:33Z", "userid": 43429, "revid": 96023401, "user": "Fropuff", "parentid": 91077754, "size": 8069}, {"comment": "/* Discrete subgroups of SU(2) */ reply", "sha1": "7cc62bd09476c71db4141736570b20c3dc69d594", "timestamp": "2006-11-30T03:46:57Z", "userid": 43429, "revid": 91077754, "user": "Fropuff", "parentid": 89769128, "size": 7478}, {"comment": "/* Discrete subgroups of SU(2) */", "sha1": "2bd6115d32ac700d7084f944e4e4288026fccdd1", "timestamp": "2006-11-24T04:24:44Z", "userid": 609725, "revid": 89769128, "user": "Tamfang", "parentid": 89414222, "size": 6979}, {"comment": "", "sha1": "0e5f80af4e1f8c5ba87c802c94e36c18ef20be75", "timestamp": "2006-11-22T08:52:40Z", "userid": 1901001, "revid": 89414222, "user": "Hillgentleman", "parentid": 56537932, "size": 6907}, {"comment": "/* Topological proof */ reply", "sha1": "ae33ef68ee1de0f418b8aa22ca4c6b2f5358ed47", "timestamp": "2006-06-02T18:38:10Z", "userid": 43429, "revid": 56537932, "user": "Fropuff", "parentid": 56497145, "size": 6789}, {"comment": "Topological proof", "sha1": "7ef78271c0716e1384066b4320a942fbe107191d", "timestamp": "2006-06-02T14:08:02Z", "userid": 346060, "revid": 56497145, "user": "Mgnbar", "parentid": 41911790, "size": 6519}, {"comment": "/* Proof */ topological proof back in", "sha1": "47f293429116b9190939f2fbfc460524a668463f", "timestamp": "2006-03-02T15:48:24Z", "userid": 346060, "revid": 41911790, "user": "Mgnbar", "parentid": 36569103, "size": 5104}, {"comment": "/* will somebody explain */", "sha1": "6aa98734c21adb709fc9e83303be5305acb69420", "timestamp": "2006-01-25T00:03:16Z", "userid": 212526, "revid": 36569103, "user": "Salix alba", "parentid": 36565083, "size": 4800}, {"comment": "", "sha1": "e5aecdd397223bd2ed134cadd6a3cd27ec6d907e", "timestamp": "2006-01-24T23:32:16Z", "userid": 0, "revid": 36565083, "anon": "", "user": "68.236.23.222", "parentid": 22831876, "size": 4606}, {"comment": "", "sha1": "3d4d099494416815d304af92a79694505415eb88", "timestamp": "2005-09-08T09:23:02Z", "userid": 0, "revid": 22831876, "anon": "", "user": "66.109.195.89", "parentid": 15920667, "size": 4501}, {"comment": "/* will somebody explain */ reply", "sha1": "3847b967960f7d01e250c42b44bbd01483e119ce", "timestamp": "2005-03-22T10:06:56Z", "userid": 12978, "revid": 15920667, "user": "Charles Matthews", "parentid": 11389161, "size": 4446}, {"comment": "will somebody explain", "sha1": "0a7ada95042f2057508dcdd4b0600352c062d3d4", "timestamp": "2005-03-22T04:43:19Z", "userid": 0, "revid": 11389161, "anon": "", "user": "72.19.73.209", "parentid": 11383938, "size": 4321}, {"comment": "", "sha1": "6e1bdd3e34835033bd18542128393f2b391b838a", "timestamp": "2004-11-19T12:11:06Z", "userid": 102403, "revid": 11383938, "user": "Spug", "parentid": 7643702, "size": 4238}, {"comment": "", "sha1": "5d5250b637aa20807f1468b1d489be6d525e6eb8", "timestamp": "2004-11-18T20:01:17Z", "userid": 120598, "revid": 7643702, "user": "Transfinite", "parentid": 7618540, "size": 3923}, {"comment": "", "sha1": "1e4d2de05b97b57c8ef98626fdcd86cca211d478", "timestamp": "2004-11-18T19:58:32Z", "userid": 120598, "revid": 7618540, "user": "Transfinite", "parentid": 7618459, "size": 3918}, {"comment": "external link missing", "sha1": "96689b388591dde5bc47b7e93f979b599230cd56", "timestamp": "2004-10-21T18:28:00Z", "userid": 0, "revid": 7618459, "anon": "", "user": "213.89.222.61", "parentid": 6755499, "size": 3374}, {"comment": "contents of 'platonic solids'", "sha1": "ba6b5b9e46db7be09f5c63b9f90435f2c856a0d4", "timestamp": "2004-09-21T07:48:03Z", "userid": 12978, "revid": 6755499, "user": "Charles Matthews", "parentid": 6034494, "size": 3173}, {"comment": "User", "sha1": "45c9c3e1bff7760a437a63ee20e73b16746fca03", "timestamp": "2004-08-05T17:19:54Z", "userid": 31280, "revid": 6034494, "user": "Texture", "parentid": 5019566, "size": 1564}, {"comment": "oops", "sha1": "2b031f1fe88829ea555a929cdebf7df2eb77bdff", "timestamp": "2004-06-14T14:32:52Z", "userid": 37304, "revid": 5019566, "user": "Tosha", "parentid": 4085996, "size": 1560}, {"comment": "", "sha1": "7ee45cb0bfc3a24f13a6d55b9dd7b5b6b4e184fd", "timestamp": "2004-06-14T14:31:39Z", "userid": 37304, "revid": 4085996, "user": "Tosha", "parentid": 4085983, "size": 1558}, {"comment": "Re: images", "sha1": "f0e820e94b894cde3db06403ba8dbb389e2286cd", "timestamp": "2003-05-30T22:23:22Z", "userid": 7586, "revid": 4085983, "user": "Cyp", "parentid": 980430, "size": 1222}, {"comment": "Images", "sha1": "e1824410ef1b84094d29fadc627dec14e1852cc7", "timestamp": "2003-05-02T03:55:26Z", "userid": 10317, "revid": 980430, "user": "Astudent", "parentid": 881087, "size": 1099}, {"comment": "classical elements", "sha1": "fddf42247a341b1062ecc23d242f21162d529215", "timestamp": "2003-04-28T10:54:03Z", "userid": 4558, "revid": 881087, "user": "JohnOwens", "parentid": 870623, "size": 978}, {"comment": "Automated conversion", "sha1": "82a910ba5e05d3f2a967ad93845bbc32d5e3da22", "timestamp": "2002-02-25T15:51:15Z", "userid": 0, "revid": 870623, "anon": "", "user": "Conversion script", "parentid": 274525, "size": 464}, {"comment": "edges", "sha1": "f06751e280172131271063d359cb2173c3d66bb4", "timestamp": "2001-12-20T14:52:19Z", "userid": 0, "revid": 274525, "anon": "", "user": "132.204.25.xxx", "parentid": 274524, "size": 121}, {"comment": "symmetry groups need an explanation", "sha1": "852088dc5092922ef35075160dcf0e56abee4201", "timestamp": "2001-09-08T20:54:11Z", "userid": 2, "revid": 274524, "user": "AxelBoldt", "parentid": 0, "size": 58}]}