{"lastrevid": 631916383, "pageid": 6015268, "canonicalurl": "http://en.wikipedia.org/wiki/Talk:Pons_asinorum", "links": [{"ns": 0, "title": "History of the Pythagorean theorem"}, {"ns": 0, "title": "Isosceles triangle theorem"}, {"ns": 0, "title": "Mathematics"}, {"ns": 0, "title": "Pons asinorum"}, {"ns": 0, "title": "Pythagorean theorem"}, {"ns": 0, "title": "Theorem on isosceles triangles"}], "title": "Talk:Pons asinorum", "editurl": "http://en.wikipedia.org/w/index.php?title=Talk:Pons_asinorum&action=edit", "contentmodel": "wikitext", "length": 4770, "pagelanguage": "en", "touched": "2015-04-08T12:32:51Z", "ns": 1, "fullurl": "http://en.wikipedia.org/wiki/Talk:Pons_asinorum", "categories": [{"ns": 14, "title": "Category:B-Class mathematics articles"}, {"ns": 14, "title": "Category:Mathematics articles related to history of mathematics"}, {"ns": 14, "title": "Category:Mid-Priority mathematics articles"}], "revisions": [{"comment": "/* Merger proposal */ done", "sha1": "87da9bdaeaaa2cebc1b33178c5cea4fcfce295da", "timestamp": "2014-10-31T18:11:49Z", "userid": 2051880, "revid": 631916383, "user": "David Eppstein", "parentid": 572626223, "size": 4770}, {"comment": "/* Merger proposal */ Comment", "sha1": "f181912a1da9e853721ea01bf7f3db02b03345d2", "timestamp": "2013-09-12T14:15:27Z", "userid": 433687, "revid": 572626223, "user": "RDBury", "parentid": 558962219, "size": 4485}, {"comment": "/* Merger proposal */", "sha1": "a9972d2cd59f4378b2981874b858b7cf89b142b4", "timestamp": "2013-06-08T21:08:53Z", "userid": 19120357, "revid": 558962219, "user": "Chen10k2", "parentid": 558962081, "size": 4269}, {"comment": "/* Merger proposal */ new section", "sha1": "c48cbd1d4f3ba4d049225d95d64984531dc22da1", "timestamp": "2013-06-08T21:07:35Z", "userid": 19120357, "revid": 558962081, "user": "Chen10k2", "parentid": 545092806, "size": 4294}, {"comment": "/* No difference */", "sha1": "e452a6dde0c3307d5b7e884df8a5ba1d40b7ee4b", "timestamp": "2013-03-18T00:02:15Z", "userid": 0, "revid": 545092806, "anon": "", "user": "96.248.226.133", "parentid": 545091047, "size": 3570}, {"comment": "/* No difference */", "sha1": "7462990c8f28a4fe0a34dd1887f5c7bd79a1fa7e", "timestamp": "2013-03-17T23:53:24Z", "userid": 0, "revid": 545091047, "anon": "", "user": "96.248.226.133", "parentid": 429532273, "size": 3518}, {"comment": "Signing comment by [[Special:Contributions/76.119.233.112|76.119.233.112]] - \"\"", "sha1": "256eaee6d911a69f2a63b8d726930c9291f16daa", "timestamp": "2011-05-17T09:29:39Z", "userid": 4936590, "revid": 429532273, "user": "SineBot", "parentid": 429532155, "size": 3314}, {"comment": "", "sha1": "fac95a155c7bc8c3acc9100ecfe5f0b7c403850b", "timestamp": "2011-05-17T09:28:27Z", "userid": 0, "revid": 429532155, "anon": "", "user": "76.119.233.112", "parentid": 416243837, "size": 3015}, {"comment": "/* No difference */", "sha1": "81806842d90d8098d5528427d5c69ba9c86977db", "timestamp": "2011-02-27T18:54:53Z", "userid": 0, "revid": 416243837, "anon": "", "user": "98.240.230.81", "parentid": 340188594, "size": 2517}, {"comment": "++Class, article is short by B standards but I think all the major facts are covered.", "sha1": "ac24ea6f09499db9c619dcb6472139b4335205b8", "timestamp": "2010-01-26T19:39:51Z", "userid": 433687, "revid": 340188594, "user": "RDBury", "parentid": 339734761, "size": 2221}, {"comment": "/* Original diagram of pons asinorum */ picture", "sha1": "0a5f840520b12f9fa2e98d98005ed7be14b80217", "timestamp": "2010-01-24T15:21:36Z", "userid": 3784322, "revid": 339734761, "user": "Dmcq", "parentid": 339728400, "size": 2225}, {"comment": "/* Original diagram of pons asinorum */ Response", "sha1": "456a202e139a137fb511e11a2699ef10fe145e26", "timestamp": "2010-01-24T14:35:59Z", "userid": 433687, "revid": 339728400, "user": "RDBury", "parentid": 339710069, "size": 2055}, {"comment": "/* Original diagram of pons asinorum */ typo", "sha1": "d4d0aff0403f61ce430490c087b4e8b5064d9354", "timestamp": "2010-01-24T11:53:21Z", "userid": 3784322, "revid": 339710069, "user": "Dmcq", "parentid": 339710016, "size": 1734}, {"comment": "/* Original diagram of pons asinorum */ new section", "sha1": "69e8eda0353a17fa0d1c004c43b626f841d3daf7", "timestamp": "2010-01-24T11:52:49Z", "userid": 3784322, "revid": 339710016, "user": "Dmcq", "parentid": 339602869, "size": 1733}, {"comment": "++Class", "sha1": "f0f129a137c5ed49532f57cac637f5c8e1cc5811", "timestamp": "2010-01-23T21:34:11Z", "userid": 433687, "revid": 339602869, "user": "RDBury", "parentid": 339561712, "size": 1246}, {"comment": "maths rating", "sha1": "f00fa8776f8107b6e3a469ba28e55df5e087cfda", "timestamp": "2010-01-23T17:26:09Z", "userid": 433687, "revid": 339561712, "user": "RDBury", "parentid": 339561466, "size": 1245}, {"comment": "Retroactive section title", "sha1": "80211d94bb8a6349e44d4bb0b4f8a539f12ce98a", "timestamp": "2010-01-23T17:24:27Z", "userid": 433687, "revid": 339561466, "user": "RDBury", "parentid": 339561334, "size": 1187}, {"comment": "/* Content fork */ new section", "sha1": "c645adb43f2894798aaed9bb9adfd4eb84ab7985", "timestamp": "2010-01-23T17:23:38Z", "userid": 433687, "revid": 339561334, "user": "RDBury", "parentid": 124658033, "size": 1170}, {"comment": "/* No difference */", "sha1": "bc3acef96aaeafe8a3c591480cc8a0d30ba7cd84", "timestamp": "2007-04-21T18:46:26Z", "userid": 0, "revid": 124658033, "anon": "", "user": "81.231.32.208", "parentid": 113582328, "size": 710}, {"comment": "ABC is ACB", "sha1": "cc6b6639744f7fd6cc0f33fc10cd3cdc1194335b", "timestamp": "2007-03-08T15:02:50Z", "userid": 36267, "revid": 113582328, "user": "Unfree", "parentid": 64486105, "size": 433}, {"comment": "Aristotle vs Euclid", "sha1": "75340e96c1a8848feabb447a485d28838fe2b201", "timestamp": "2006-07-18T15:57:50Z", "userid": 0, "revid": 64486105, "anon": "", "user": "64.166.207.90", "parentid": 0, "size": 288}]}